{
	"Awesome ETHS": {
		"source": "https://github.com/chromezoneeths/awesome-eths",
		"deployment": "https://chromezoneeths.github.io/awesome-eths",
		"description": "This website!",
		"authors": [
			"Willow Carlson-Huber"
		],
		"categories": [
			"CodETHS",
			"Awesome Lists"
		]
	},
	"ETHSBell Rewrite": {
		"source": "https://github.com/chromezoneeths/ethsbell-rewrite",
		"deployment": "https://bell-dev.wolo.dev",
		"description": "A re-write of ETHSBell with some extra features.",
		"authors": [
			"Willow Carlson-Huber"
		],
		"categories": [
			"CodETHS",
			"Application",
			"Web API"
		]
	}
}